setup.py
corenlp_xml/__init__.py
corenlp_xml/coreference.py
corenlp_xml/dependencies.py
corenlp_xml/document.py
corenlp_xml.egg-info/PKG-INFO
corenlp_xml.egg-info/SOURCES.txt
corenlp_xml.egg-info/dependency_links.txt
corenlp_xml.egg-info/requires.txt
corenlp_xml.egg-info/top_level.txt
test/test.py
test/test_coreference.py
test/test_dependencies.py
test/test_document.py