Metadata-Version: 1.0
Name: corenlp-xml
Version: 1.0.0
Summary: Library for interacting with the XML output of the Stanford CoreNLP pipeline.
Home-page: https://github.com/relwell/corenlp-xml-lib
Author: Robert Elwell
Author-email: robert.elwell@gmail.com
License: Other
Platform: UNKNOWN
